Emailer/VERSION
Emailer/__init__.py
Emailer/core.py
Emailer/template_types.py
Emailer/version.py
Emailer-1.1.dist-info/LICENSE.md
Emailer-1.1.dist-info/METADATA
Emailer-1.1.dist-info/WHEEL
Emailer-1.1.dist-info/top_level.txt
Emailer-1.1.dist-info/RECORD
