Metadata-Version: 2.1
Name: Emailer
Version: 1.1
Summary: Email sender
Home-page: https://github.com/QuackCoding/Emailer
Author: Aiden (Dev)
Author-email: 
License: UNKNOWN
Keywords: python,HTML,Email,email sender,Emailer,Mail
Platform: UNKNOWN
Classifier: Development Status :: 5 - Production/Stable
Classifier: Intended Audience :: Developers
Classifier: Programming Language :: Python :: 3
Classifier: Operating System :: Unix
Classifier: Operating System :: MacOS :: MacOS X
Classifier: Operating System :: Microsoft :: Windows
Requires-Dist: HTMLTemplateRender
